{
	"name": "sbdtoolkit",
	"title": "SBD Toolkit",
	"description": "<p>송버드 툴킷</p>",
	"version": "1.0.1",
	"minimumCoreVersion" : "0.8.0",
	"compatibleCoreVersion": "0.8.8",
	"author": "mrkb",
	"esmodules": [],
	"scripts": [],
	"styles": ["style.css"],
	"packs": [
    {
		"label": "SBD Toolkit",
		"entity": "JournalEntry",
		"name": "journal",
		"path": "journal.db",
		"module": "sbdtoolkit"
    }
	],
	"languages": [],
	"url": "https://github.com/MaronKB/sbdtoolkit",
	"manifest": "https://raw.githubusercontent.com/MaronKB/sbdtoolkit/main/module.json",
	"download": "https://github.com/MaronKB/sbdtoolkit/archive/main.zip"
}
